[
    {
        "batch_name": "NSEC 2024",
        "batch_class": "11th",
        "batch_id": "65a695da8a61460018ccc7eb",
        "batch_slug": "nsec-2024-442293",
        "batch_banner": "https://d2bps9p1kiy4ka.cloudfront.net/5eb393ee95fab7468a79d189/e0b7533e-9366-43a7-9492-f3c2e784e463.jpeg",
        "batch_exam": "OLYMPIAD"
    },
    {
        "batch_name": "NSEC",
        "batch_class": "11th",
        "batch_id": "64d23a31fa04f200188b5699",
        "batch_slug": "nsec-250965",
        "batch_banner": "https://static.pw.live/5eb393ee95fab7468a79d189/a5866500-d892-47bd-9659-6fb3fbb6a9ea.png",
        "batch_exam": "OLYMPIAD"
    }
]