[
    {
        "batch_name": "CLAT Kaksha 2025 Morning Batch",
        "batch_class": "12th+",
        "batch_id": "666d5521211c700018f803d1",
        "batch_slug": "clat-kaksha-2025-morning-batch-181573",
        "batch_banner": "https://static.pw.live/5eb393ee95fab7468a79d189/ADMIN/318e6d2a-7c05-4567-bf60-8593d67a1dc5.jpg",
        "batch_exam": "LAW"
    },
    {
        "batch_name": "CLAT 2025 Success Strategy Batch",
        "batch_class": "12th+",
        "batch_id": "6692c4d9374c7f0018ed6304",
        "batch_slug": "clat-2025-success-strategy-batch-463646",
        "batch_banner": "https://static.pw.live/5eb393ee95fab7468a79d189/ADMIN/e923b6ab-8a95-4b33-949d-44b81e499558.png",
        "batch_exam": "LAW"
    },
    {
        "batch_name": "Law Webinar Batch",
        "batch_class": "12th+",
        "batch_id": "667031f4ebb2bc0018c398b0",
        "batch_slug": "law-webinar-batch-580302",
        "batch_banner": "https://graph.org/file/42082165097e0a0a287f8.jpg",
        "batch_exam": "LAW"
    },
    {
        "batch_name": "CLAT NEXUS 3.0 INTERMEDIATE 2025 BATCH",
        "batch_class": "12th+",
        "batch_id": "6655890a65946b00187fed2c",
        "batch_slug": "clat-nexus-3-0-intermediate-2025-batch-832224",
        "batch_banner": "https://d2bps9p1kiy4ka.cloudfront.net/5eb393ee95fab7468a79d189/fabce8af-ed2e-4f94-a2de-7eb4e663b5fc.png",
        "batch_exam": "LAW"
    },
    {
        "batch_name": "CLAT Zenith 2026 Batch",
        "batch_class": "12th+",
        "batch_id": "6639c8490ac5c300186ff2a3",
        "batch_slug": "clat-zenith-2026-batch-944206",
        "batch_banner": "https://d2bps9p1kiy4ka.cloudfront.net/5eb393ee95fab7468a79d189/02bb754c-caf4-408e-9c08-4d40e67ea88c.png",
        "batch_exam": "LAW"
    },
    {
        "batch_name": "CLAT NEXUS 2.0 2025",
        "batch_class": "12th+",
        "batch_id": "6613ec63eefcfd001876c661",
        "batch_slug": "clat-nexus-2-0-2025-406003",
        "batch_banner": "https://d2bps9p1kiy4ka.cloudfront.net/5eb393ee95fab7468a79d189/64fd0a4e-d52c-4450-874e-90b820943b1e.png",
        "batch_exam": "LAW"
    },
    {
        "batch_name": "CLAT Nexus 2025 Batch",
        "batch_class": "12th+",
        "batch_id": "65d8551308aa5a00187e2720",
        "batch_slug": "clat-nexus-2025-batch-775113",
        "batch_banner": "https://static.pw.live/5eb393ee95fab7468a79d189/fdcb12c3-6947-4fd0-a3ee-b86b3d650ed6.png",
        "batch_exam": "LAW"
    },
    {
        "batch_name": "Law Quest (OLETs) 2024 Batch",
        "batch_class": "12th+",
        "batch_id": "658bd5bdd5dfb0001888040e",
        "batch_slug": "law-quest--olets--2024-batch-498258",
        "batch_banner": "https://static.pw.live/5eb393ee95fab7468a79d189/96fb4b3b-7308-4771-a20b-a873a92bf803.png",
        "batch_exam": "LAW"
    },
    {
        "batch_name": "LAW CLAT ACHIEVERS 2024",
        "batch_class": "12th+",
        "batch_id": "646747cd35ed4c0018d30ac5",
        "batch_slug": "law-clat-achievers-2024-241958",
        "batch_banner": "https://d2bps9p1kiy4ka.cloudfront.net/5eb393ee95fab7468a79d189/53698507-fe0c-4cba-8e28-0c7096f97797.png",
        "batch_exam": "LAW"
    }
]